{"version":1,"resource":"vscode-remote://wsl%2Bubuntu-22.04/home/akraaam_kh/Paris-B2-DevWeb-main/app/public/style.css","entries":[{"id":"b9HM.css","timestamp":1710112706636},{"id":"0T97.css","source":"undoRedo.source","timestamp":1710112717494},{"id":"vn2y.css","timestamp":1710112726693},{"id":"00Ux.css","source":"undoRedo.source","timestamp":1710112729477},{"id":"WpJb.css","timestamp":1710112746057},{"id":"X7VM.css","timestamp":1710112758057},{"id":"Q9rb.css","timestamp":1710112824329},{"id":"6DC0.css","timestamp":1710112846789},{"id":"d9Zt.css","timestamp":1710112857502},{"id":"GvP0.css","timestamp":1710112904976},{"id":"SSn3.css","timestamp":1710112923060},{"id":"9NpU.css","timestamp":1710112992097},{"id":"9dOn.css","timestamp":1710113015831},{"id":"GIyl.css","timestamp":1710113525287},{"id":"8VBM.css","timestamp":1710113660036},{"id":"7jvT.css","source":"undoRedo.source","timestamp":1710113669586},{"id":"m7BS.css","timestamp":1710113672816},{"id":"M5ln.css","timestamp":1710113696210},{"id":"sSUw.css","timestamp":1710113717660},{"id":"EnhB.css","source":"undoRedo.source","timestamp":1710113735232},{"id":"ZAxY.css","timestamp":1710113741192},{"id":"e3gT.css","source":"undoRedo.source","timestamp":1710113742612},{"id":"9rSm.css","timestamp":1710113757226},{"id":"KOWw.css","timestamp":1710113793039},{"id":"IaLN.css","timestamp":1710113907624},{"id":"6VDe.css","timestamp":1710113947667},{"id":"9jDp.css","source":"undoRedo.source","timestamp":1710113957287},{"id":"ZUJ0.css","timestamp":1710113986030},{"id":"So9l.css","timestamp":1710114024335},{"id":"DyQA.css","source":"undoRedo.source","timestamp":1710114032885},{"id":"9iwo.css","timestamp":1710114066239},{"id":"ynj9.css","timestamp":1710114077789},{"id":"Xbj3.css","timestamp":1710114098164},{"id":"0BGW.css","timestamp":1710114124708},{"id":"EP4s.css","timestamp":1710114135619},{"id":"GCSY.css","timestamp":1710156548542},{"id":"faFP.css","timestamp":1710156560133},{"id":"41R6.css","timestamp":1710444554799},{"id":"zqJf.css","timestamp":1710444581563},{"id":"3ugC.css","timestamp":1710446310916},{"id":"U5sS.css","timestamp":1710446331070},{"id":"T3Tf.css","source":"undoRedo.source","timestamp":1710446339050},{"id":"2AhC.css","timestamp":1710446377474},{"id":"dOk6.css","timestamp":1710446564164},{"id":"6hrV.css","source":"undoRedo.source","timestamp":1710446572164},{"id":"E0S4.css","timestamp":1710446575264},{"id":"h6us.css","timestamp":1710446749075},{"id":"vAwY.css","timestamp":1710446812562},{"id":"XTl0.css","timestamp":1710446826532},{"id":"Hnfe.css","timestamp":1710861303006}]}