{"version":1,"resource":"vscode-remote://wsl%2Bubuntu-22.04/home/akraaam_kh/Paris-B2-DevWeb-main/app/public/historique.php","entries":[{"id":"BlcZ.php","timestamp":1710156668585},{"id":"HH0K.php","timestamp":1710156772209},{"id":"ozY0.php","timestamp":1710156809172},{"id":"gbDG.php","source":"undoRedo.source","timestamp":1710156810231},{"id":"wVTl.php","timestamp":1710156855453},{"id":"2YrY.php","timestamp":1710156881277},{"id":"bl8Z.php","timestamp":1710157032106},{"id":"ZgPh.php","timestamp":1710157085573},{"id":"QRkz.php","timestamp":1710157107370},{"id":"jh1F.php","timestamp":1710157142195},{"id":"DzKH.php","timestamp":1710157232199},{"id":"H6HW.php","timestamp":1710157275689},{"id":"i4bP.php","timestamp":1710157293626},{"id":"XtoL.php","timestamp":1710157327111},{"id":"B0dv.php","timestamp":1710157551537},{"id":"3Jsf.php","timestamp":1710157590160},{"id":"9x55.php","timestamp":1710157697403},{"id":"YVF6.php","source":"undoRedo.source","timestamp":1710157705753},{"id":"1Enk.php","timestamp":1710157902523},{"id":"5gQG.php","timestamp":1710158272361},{"id":"diHZ.php","timestamp":1710158981696}]}